dib3_utils.py
dib3_utils-0.1.1.dist-info/METADATA
dib3_utils-0.1.1.dist-info/WHEEL
dib3_utils-0.1.1.dist-info/RECORD
