Metadata-Version: 2.1
Name: dib3-utils
Version: 0.1.1
Summary: Biblioteca com ferramentas úteis para cálculos com contratos de depósitos interbancários (DI) da B3.
Author: renanmoretto
Author-email: himynameisrenan@outlook.com
Requires-Python: >=3.10,<4.0
Classifier: Programming Language :: Python :: 3
Classifier: Programming Language :: Python :: 3.10
Classifier: Programming Language :: Python :: 3.11
Classifier: Programming Language :: Python :: 3.12
Requires-Dist: dias-uteis (>=0.1.13,<0.2.0)
